{
  "articles": [
    {
      "id": "1",
      "title": "Tarte aux Pommes",
      "description": "Une délicieuse tarte aux pommes avec une croûte dorée.",
      "image": "https://encrypted-tbn0.gstatic.com/images?q=tbn:ANd9GcTEaq6BRJKmVeKte2kueb2r86JrRazc0syiiw&s",
      "category": "Desserts",
      "price": "8.50€"
    },
    {
      "id": "2",
      "title": "Poulet Rôti",
      "description": "Un poulet rôti juteux et savoureux, parfait pour un dîner en famille.",
      "image": "https://www.apero-bordeaux.fr/wp-content/uploads/2024/02/20240216_65cfa1ce1fa54.jpg",
      "category": "Plats Principaux",
      "price": "15.00€"
    },
    {
      "id": "3",
      "title": "Salade César",
      "description": "Une salade César classique avec une vinaigrette maison.",
      "image": "https://img.cuisineaz.com/660x660/2022/07/18/i184733-shutterstock-95710738.jpeg",
      "category": "Entrées",
      "price": "7.00€"
    },
    {
      "id": "4",
      "title": "Soupe à l'Oignon",
      "description": "Une soupe à l'oignon française traditionnelle avec du fromage gratiné.",
      "image": "https://images.getrecipekit.com/20220316211706-now-20open-20-81.png?aspect_ratio=16:9&quality=90&",
      "category": "Soupes",
      "price": "6.50€"
    },
    {
      "id": "5",
      "title": "Spaghetti Carbonara",
      "description": "Des spaghetti à la carbonara crémeux avec du bacon croustillant.",
      "image": "https://encrypted-tbn0.gstatic.com/images?q=tbn:ANd9GcSPSi0trCfR2xYQVkUw3F8t-GVj-Cr14F7ZlA&s",
      "category": "Plats Principaux",
      "price": "12.00€"
    },
    {
      "id": "6",
      "title": "Brownies au Chocolat",
      "description": "Des brownies au chocolat fondants avec une croûte craquante.",
      "image": "https://encrypted-tbn0.gstatic.com/images?q=tbn:ANd9GcSFr48cmKhIIjfDAbW_5fQVv1ptb_YOoW3P_w&s",
      "category": "Desserts",
      "price": "5.00€"
    },
    {
      "id": "7",
      "title": "Quiche Lorraine",
      "description": "Une quiche lorraine classique avec du bacon et du fromage.",
      "image": "https://assets.tmecosys.com/image/upload/t_web767x639/img/recipe/ras/Assets/51c16699-4f76-49dd-a39f-ed90e8a124ea/Derivates/8257865a-ff7e-4806-bb56-dd1e23ef6621.jpg",
      "category": "Entrées",
      "price": "8.00€"
    },
    {
      "id": "8",
      "title": "Ratatouille",
      "description": "Un mélange de légumes mijotés à la provençale.",
      "image": "https://encrypted-tbn0.gstatic.com/images?q=tbn:ANd9GcTEAMEe950lO85yFawnMDL_8f6GGScOGBjSLA&s",
      "category": "Accompagnements",
      "price": "9.00€"
    },
    {
      "id": "f32a",
      "title": "Tarte aux pommes",
      "description": "Une délicieuse tarte aux pommes avec une croûte dorée.",
      "image": "https://res.cloudinary.com/dnorkm6gq/image/upload/v1720404976/hgwek50iorahx9n3zrkv.jpg",
      "category": "Accompagnements",
      "price": "8.50€"
    },
    {
      "id": "cab1",
      "title": "salade césar",
      "description": ".....",
      "image": "https://res.cloudinary.com/dnorkm6gq/image/upload/v1720452554/pxcqrh632ofsjznkadbc.jpg",
      "category": "Entrées"
    }
  ],
  "categories": [
    {
      "id": "1",
      "name": "Desserts"
    },
    {
      "id": "2",
      "name": "Plats Principaux"
    },
    {
      "id": "3",
      "name": "Entrées"
    },
    {
      "id": "4",
      "name": "Soupes"
    },
    {
      "id": "5",
      "name": "Accompagnements"
    },
    {
      "id": "6",
      "name": "Plats Rapides"
    }
  ]
}